{"v":"5.6.10","fr":24,"ip":0,"op":215,"w":1336,"h":736,"nm":"Hero","ddd":0,"assets":[{"id":"image_0","w":222,"h":98,"u":"images/","p":"img_0.png","e":0},{"id":"image_1","w":19,"h":21,"u":"images/","p":"img_1.png","e":0},{"id":"image_2","w":23,"h":16,"u":"images/","p":"img_2.png","e":0},{"id":"image_3","w":20,"h":21,"u":"images/","p":"img_3.png","e":0},{"id":"image_4","w":17,"h":20,"u":"images/","p":"img_4.png","e":0},{"id":"image_5","w":20,"h":21,"u":"images/","p":"img_5.png","e":0},{"id":"image_6","w":130,"h":132,"u":"images/","p":"img_6.png","e":0},{"id":"image_7","w":150,"h":77,"u":"images/","p":"img_7.png","e":0},{"id":"image_8","w":125,"h":31,"u":"images/","p":"img_8.png","e":0},{"id":"comp_0","layers":[{"ddd":0,"ind":1,"ty":2,"nm":"Busqueda 2","refId":"image_0","sr":1,"ks":{"o":{"a":0,"k":100},"r":{"a":0,"k":0},"p":{"a":1,"k":[{"i":{"x":0.667,"y":1},"o":{"x":0.333,"y":0},"t":16,"s":[1193.871,341.597,0],"to":[0,2.167,0],"ti":[0,0,0]},{"i":{"x":0.667,"y":1},"o":{"x":0.333,"y":0},"t":66,"s":[1193.871,354.597,0],"to":[0,0,0],"ti":[0,0,0]},{"i":{"x":0.667,"y":1},"o":{"x":0.167,"y":0},"t":111,"s":[1193.871,341.597,0],"to":[0,0,0],"ti":[0,0,0]},{"i":{"x":0.667,"y":1},"o":{"x":0.167,"y":0},"t":162,"s":[1193.871,354.597,0],"to":[0,0,0],"ti":[0,2.167,0]},{"t":214,"s":[1193.871,341.597,0]}]},"a":{"a":0,"k":[110.572,48.879,0]},"s":{"a":1,"k":[{"i":{"x":[0.667,0.667,0.667],"y":[1,1,1]},"o":{"x":[0.333,0.333,0.333],"y":[0,0,0]},"t":15,"s":[0,0,100]},{"i":{"x":[0.667,0.667,0.667],"y":[1,1,1]},"o":{"x":[0.333,0.333,0.333],"y":[0,0,0]},"t":19,"s":[110,110,100]},{"i":{"x":[0.667,0.667,0.667],"y":[1,1,1]},"o":{"x":[0.333,0.333,0.333],"y":[0,0,0]},"t":22,"s":[94,94,100]},{"t":25,"s":[100,100,100]}]}},"ao":0,"ip":0,"op":216,"st":0,"bm":0},{"ddd":0,"ind":2,"ty":0,"nm":"Pie chart","refId":"comp_1","sr":1,"ks":{"o":{"a":0,"k":100},"r":{"a":0,"k":0},"p":{"a":1,"k":[{"i":{"x":0.667,"y":1},"o":{"x":0.333,"y":0},"t":20,"s":[887,337,0],"to":[0,1.333,0],"ti":[0,0,0]},{"i":{"x":0.667,"y":1},"o":{"x":0.333,"y":0},"t":58,"s":[887,345,0],"to":[0,0,0],"ti":[0,0,0]},{"i":{"x":0.667,"y":1},"o":{"x":0.167,"y":0},"t":106,"s":[887,337,0],"to":[0,0,0],"ti":[0,0,0]},{"i":{"x":0.667,"y":1},"o":{"x":0.167,"y":0},"t":161,"s":[887,345,0],"to":[0,0,0],"ti":[0,1.333,0]},{"t":216,"s":[887,337,0]}]},"a":{"a":0,"k":[878,261,0]},"s":{"a":0,"k":[100,100,100]}},"ao":0,"w":1366,"h":736,"ip":0,"op":240,"st":0,"bm":0},{"ddd":0,"ind":3,"ty":2,"nm":"Passaport 2","refId":"image_7","sr":1,"ks":{"o":{"a":0,"k":100},"r":{"a":0,"k":0},"p":{"a":1,"k":[{"i":{"x":0.667,"y":1},"o":{"x":0.333,"y":0},"t":12,"s":[844.848,571.857,0],"to":[0,1,0],"ti":[0,0,0]},{"i":{"x":0.667,"y":1},"o":{"x":0.333,"y":0},"t":61,"s":[844.848,577.857,0],"to":[0,0,0],"ti":[0,0,0]},{"i":{"x":0.667,"y":1},"o":{"x":0.167,"y":0},"t":111,"s":[844.848,571.857,0],"to":[0,0,0],"ti":[0,0,0]},{"i":{"x":0.667,"y":1},"o":{"x":0.167,"y":0},"t":159,"s":[844.848,577.857,0],"to":[0,0,0],"ti":[0,1,0]},{"t":215,"s":[844.848,571.857,0]}]},"a":{"a":0,"k":[74.799,38.258,0]},"s":{"a":1,"k":[{"i":{"x":[0.667,0.667,0.667],"y":[1,1,1]},"o":{"x":[0.333,0.333,0.333],"y":[0,0,0]},"t":6,"s":[0,0,100]},{"i":{"x":[0.667,0.667,0.667],"y":[1,1,1]},"o":{"x":[0.333,0.333,0.333],"y":[0,0,0]},"t":10,"s":[110,110,100]},{"i":{"x":[0.667,0.667,0.667],"y":[1,1,1]},"o":{"x":[0.333,0.333,0.333],"y":[0,0,0]},"t":13,"s":[94,94,100]},{"t":16,"s":[100,100,100]}]}},"ao":0,"ip":0,"op":216,"st":0,"bm":0},{"ddd":0,"ind":4,"ty":0,"nm":"Maleta","refId":"comp_2","sr":1,"ks":{"o":{"a":0,"k":100},"r":{"a":0,"k":0},"p":{"a":0,"k":[683,368,0]},"a":{"a":0,"k":[683,368,0]},"s":{"a":0,"k":[100,100,100]}},"ao":0,"w":1366,"h":736,"ip":0,"op":240,"st":0,"bm":0}]},{"id":"comp_1","layers":[{"ddd":0,"ind":1,"ty":2,"nm":"Restaurant","refId":"image_1","sr":1,"ks":{"o":{"a":0,"k":100},"r":{"a":0,"k":0},"p":{"a":0,"k":[887.613,350.193,0]},"a":{"a":0,"k":[9.25,10.25,0]},"s":{"a":1,"k":[{"i":{"x":[0.667,0.667,0.667],"y":[1,1,1]},"o":{"x":[0.333,0.333,0.333],"y":[0,0,0]},"t":20,"s":[0,0,100]},{"i":{"x":[0.667,0.667,0.667],"y":[1,1,1]},"o":{"x":[0.333,0.333,0.333],"y":[0,0,0]},"t":24,"s":[110,110,100]},{"i":{"x":[0.667,0.667,0.667],"y":[1,1,1]},"o":{"x":[0.333,0.333,0.333],"y":[0,0,0]},"t":27,"s":[94,94,100]},{"t":30,"s":[100,100,100]}]}},"ao":0,"ip":0,"op":240,"st":0,"bm":0},{"ddd":0,"ind":2,"ty":2,"nm":"hotel","refId":"image_2","sr":1,"ks":{"o":{"a":0,"k":100},"r":{"a":0,"k":0},"p":{"a":0,"k":[951.097,307.129,0]},"a":{"a":0,"k":[11.25,7.75,0]},"s":{"a":1,"k":[{"i":{"x":[0.667,0.667,0.667],"y":[1,1,1]},"o":{"x":[0.333,0.333,0.333],"y":[0,0,0]},"t":18,"s":[0,0,100]},{"i":{"x":[0.667,0.667,0.667],"y":[1,1,1]},"o":{"x":[0.333,0.333,0.333],"y":[0,0,0]},"t":22,"s":[110,110,100]},{"i":{"x":[0.667,0.667,0.667],"y":[1,1,1]},"o":{"x":[0.333,0.333,0.333],"y":[0,0,0]},"t":25,"s":[94,94,100]},{"t":28,"s":[100,100,100]}]}},"ao":0,"ip":0,"op":240,"st":0,"bm":0},{"ddd":0,"ind":3,"ty":2,"nm":"avion","refId":"image_3","sr":1,"ks":{"o":{"a":0,"k":100},"r":{"a":0,"k":0},"p":{"a":0,"k":[951.855,203.665,0]},"a":{"a":0,"k":[9.75,10.205,0]},"s":{"a":1,"k":[{"i":{"x":[0.667,0.667,0.667],"y":[1,1,1]},"o":{"x":[0.333,0.333,0.333],"y":[0,0,0]},"t":16,"s":[0,0,100]},{"i":{"x":[0.667,0.667,0.667],"y":[1,1,1]},"o":{"x":[0.333,0.333,0.333],"y":[0,0,0]},"t":20,"s":[110,110,100]},{"i":{"x":[0.667,0.667,0.667],"y":[1,1,1]},"o":{"x":[0.333,0.333,0.333],"y":[0,0,0]},"t":23,"s":[94,94,100]},{"t":26,"s":[100,100,100]}]}},"ao":0,"ip":0,"op":240,"st":0,"bm":0},{"ddd":0,"ind":4,"ty":2,"nm":"transporte","refId":"image_4","sr":1,"ks":{"o":{"a":0,"k":100},"r":{"a":0,"k":0},"p":{"a":0,"k":[827.774,193.952,0]},"a":{"a":0,"k":[8.25,9.75,0]},"s":{"a":1,"k":[{"i":{"x":[0.667,0.667,0.667],"y":[1,1,1]},"o":{"x":[0.333,0.333,0.333],"y":[0,0,0]},"t":14,"s":[0,0,100]},{"i":{"x":[0.667,0.667,0.667],"y":[1,1,1]},"o":{"x":[0.333,0.333,0.333],"y":[0,0,0]},"t":18,"s":[110,110,100]},{"i":{"x":[0.667,0.667,0.667],"y":[1,1,1]},"o":{"x":[0.333,0.333,0.333],"y":[0,0,0]},"t":21,"s":[94,94,100]},{"t":24,"s":[100,100,100]}]}},"ao":0,"ip":0,"op":240,"st":0,"bm":0},{"ddd":0,"ind":5,"ty":2,"nm":"others","refId":"image_5","sr":1,"ks":{"o":{"a":0,"k":100},"r":{"a":0,"k":0},"p":{"a":0,"k":[802.242,297.791,0]},"a":{"a":0,"k":[9.75,10.25,0]},"s":{"a":1,"k":[{"i":{"x":[0.667,0.667,0.667],"y":[1,1,1]},"o":{"x":[0.333,0.333,0.333],"y":[0,0,0]},"t":11,"s":[0,0,100]},{"i":{"x":[0.667,0.667,0.667],"y":[1,1,1]},"o":{"x":[0.333,0.333,0.333],"y":[0,0,0]},"t":15,"s":[110,110,100]},{"i":{"x":[0.667,0.667,0.667],"y":[1,1,1]},"o":{"x":[0.333,0.333,0.333],"y":[0,0,0]},"t":18,"s":[94,94,100]},{"t":21,"s":[100,100,100]}]}},"ao":0,"ip":0,"op":240,"st":0,"bm":0},{"ddd":0,"ind":6,"ty":2,"nm":"Pie chart","refId":"image_6","sr":1,"ks":{"o":{"a":0,"k":100},"r":{"a":1,"k":[{"i":{"x":[0],"y":[1.003]},"o":{"x":[0.521],"y":[0.002]},"t":1,"s":[-278]},{"t":19,"s":[0]}]},"p":{"a":0,"k":[876.79,259.206,0]},"a":{"a":0,"k":[64.853,65.974,0]},"s":{"a":1,"k":[{"i":{"x":[0.667,0.667,0.667],"y":[1,1,1]},"o":{"x":[0.333,0.333,0.333],"y":[0,0,0]},"t":9,"s":[0,0,100]},{"i":{"x":[0.667,0.667,0.667],"y":[1,1,1]},"o":{"x":[0.333,0.333,0.333],"y":[0,0,0]},"t":13,"s":[110,110,100]},{"i":{"x":[0.667,0.667,0.667],"y":[1,1,1]},"o":{"x":[0.333,0.333,0.333],"y":[0,0,0]},"t":16,"s":[94,94,100]},{"t":19,"s":[100,100,100]}]}},"ao":0,"ip":0,"op":240,"st":0,"bm":0}]},{"id":"comp_2","layers":[{"ddd":0,"ind":1,"ty":2,"nm":"cinta inferior 2","refId":"image_8","sr":1,"ks":{"o":{"a":0,"k":100},"r":{"a":0,"k":0},"p":{"a":1,"k":[{"i":{"x":0.667,"y":1},"o":{"x":0.333,"y":0},"t":0,"s":[1167.422,691.827,0],"to":[0,4.167,0],"ti":[0,-4.167,0]},{"t":4,"s":[1167.422,716.827,0]}]},"a":{"a":0,"k":[62.422,15.327,0]},"s":{"a":0,"k":[100,100,100]}},"ao":0,"ip":0,"op":240,"st":0,"bm":0},{"ddd":0,"ind":2,"ty":0,"nm":"Screen","refId":"comp_3","sr":1,"ks":{"o":{"a":0,"k":100},"r":{"a":0,"k":0},"p":{"a":0,"k":[1176,697,0]},"a":{"a":0,"k":[1176,697,0]},"s":{"a":1,"k":[{"i":{"x":[0.568,0.568,0.568],"y":[1,1.103,1]},"o":{"x":[0.333,0.333,0.333],"y":[0,0,0]},"t":0,"s":[100,100,100]},{"i":{"x":[0.843,0.843,0.843],"y":[1,1,1]},"o":{"x":[0.316,0.316,0.316],"y":[0,0.075,0]},"t":5,"s":[100,138.696,100]},{"t":10,"s":[100,100,100]}]}},"ao":0,"w":1366,"h":736,"ip":0,"op":240,"st":0,"bm":0},{"ddd":0,"ind":3,"ty":4,"nm":"Capa de formas 1","sr":1,"ks":{"o":{"a":0,"k":100},"r":{"a":0,"k":0},"p":{"a":1,"k":[{"i":{"x":0.667,"y":1},"o":{"x":0.333,"y":0},"t":9,"s":[1191.5,552.25,0],"to":[1.333,-5.417,0],"ti":[-1.333,5.417,0]},{"t":13,"s":[1199.5,519.75,0]}]},"a":{"a":0,"k":[525,142,0]},"s":{"a":0,"k":[100,100,100]}},"ao":0,"shapes":[{"ty":"gr","it":[{"ind":0,"ty":"sh","ks":{"a":0,"k":{"i":[[0,0],[0,0],[0,0],[0,0]],"o":[[0,0],[0,0],[0,0],[0,0]],"v":[[488.25,159],[497,127],[560,127],[552.5,158.5]],"c":false}},"nm":"Trazado 1","hd":false},{"ty":"st","c":{"a":0,"k":[0.768627989526,0.768627989526,0.768627989526,1]},"o":{"a":0,"k":100},"w":{"a":0,"k":7},"lc":1,"lj":2,"bm":0,"nm":"Trazo 1","hd":false},{"ty":"tr","p":{"a":0,"k":[0,0]},"a":{"a":0,"k":[0,0]},"s":{"a":0,"k":[100,100]},"r":{"a":0,"k":0},"o":{"a":0,"k":100},"sk":{"a":0,"k":0},"sa":{"a":0,"k":0},"nm":"Transform"}],"nm":"Forma 1","bm":0,"hd":false}],"ip":9,"op":249,"st":9,"bm":0},{"ddd":0,"ind":4,"ty":2,"nm":"cinta inferior","refId":"image_8","sr":1,"ks":{"o":{"a":0,"k":100},"r":{"a":0,"k":0},"p":{"a":0,"k":[1167.422,715.827,0]},"a":{"a":0,"k":[62.422,15.327,0]},"s":{"a":0,"k":[100,100,100]}},"ao":0,"ip":0,"op":240,"st":0,"bm":0},{"ddd":0,"ind":5,"ty":4,"nm":"Trasera inferior contornos","sr":1,"ks":{"o":{"a":0,"k":100},"r":{"a":0,"k":0},"p":{"a":0,"k":[1162.309,716.309,0]},"a":{"a":0,"k":[106.558,21.059,0]},"s":{"a":0,"k":[100,100,100]}},"ao":0,"shapes":[{"ty":"gr","it":[{"ind":0,"ty":"sh","ks":{"a":0,"k":{"i":[[3.403,0],[0,0],[0,3.403],[0,0],[-3.403,0],[0,0],[0,-3.403],[0,0]],"o":[[0,0],[-3.403,0],[0,0],[0,-3.403],[0,0],[3.403,0],[0,0],[0,3.403]],"v":[[95.396,16.059],[-95.397,16.059],[-101.559,9.896],[-101.559,-9.897],[-95.397,-16.059],[95.396,-16.059],[101.559,-9.897],[101.559,9.896]],"c":true}},"nm":"Trazado 1","hd":false},{"ty":"st","c":{"a":0,"k":[0.769000004787,0.769000004787,0.769000004787,1]},"o":{"a":0,"k":100},"w":{"a":0,"k":2},"lc":1,"lj":1,"ml":10,"bm":0,"nm":"Trazo 1","hd":false},{"ty":"tr","p":{"a":0,"k":[106.564,20.707]},"a":{"a":0,"k":[0,0]},"s":{"a":0,"k":[100,100]},"r":{"a":0,"k":0},"o":{"a":0,"k":100},"sk":{"a":0,"k":0},"sa":{"a":0,"k":0},"nm":"Transform"}],"nm":"Grupo 1","bm":0,"hd":false},{"ty":"gr","it":[{"ind":0,"ty":"sh","ks":{"a":0,"k":{"i":[[3.403,0],[0,0],[0,3.403],[0,0],[-3.403,0],[0,0],[0,-3.403],[0,0]],"o":[[0,0],[-3.403,0],[0,0],[0,-3.403],[0,0],[3.403,0],[0,0],[0,3.403]],"v":[[95.396,16.059],[-95.397,16.059],[-101.559,9.896],[-101.559,-9.897],[-95.397,-16.059],[95.396,-16.059],[101.559,-9.897],[101.559,9.896]],"c":true}},"nm":"Trazado 1","hd":false},{"ty":"fl","c":{"a":0,"k":[0.969000004787,0.969000004787,0.969000004787,1]},"o":{"a":0,"k":100},"r":1,"bm":0,"nm":"Relleno 1","hd":false},{"ty":"tr","p":{"a":0,"k":[106.558,21.059]},"a":{"a":0,"k":[0,0]},"s":{"a":0,"k":[100,100]},"r":{"a":0,"k":0},"o":{"a":0,"k":100},"sk":{"a":0,"k":0},"sa":{"a":0,"k":0},"nm":"Transform"}],"nm":"Grupo 2","bm":0,"hd":false}],"ip":0,"op":240,"st":0,"bm":0},{"ddd":0,"ind":6,"ty":4,"nm":"Lateral izquierdo contornos","sr":1,"ks":{"o":{"a":0,"k":100},"r":{"a":0,"k":0},"p":{"a":0,"k":[1062.662,715.788,0]},"a":{"a":0,"k":[76.979,21.058,0]},"s":{"a":0,"k":[142.197,100,100]}},"ao":0,"shapes":[{"ty":"gr","it":[{"ind":0,"ty":"sh","ks":{"a":0,"k":{"i":[[3.403,0],[0,0],[0,3.403],[0,0],[-3.403,0],[0,0],[0,-3.403],[0,0]],"o":[[0,0],[-3.403,0],[0,0],[0,-3.403],[0,0],[3.403,0],[0,0],[0,3.403]],"v":[[119.265,16.173],[-65.818,16.059],[-71.979,9.896],[-71.979,-9.896],[-65.818,-16.059],[119.265,-15.944],[125.427,-9.782],[125.427,10.011]],"c":true}},"nm":"Trazado 1","hd":false},{"ty":"st","c":{"a":0,"k":[0.769000004787,0.769000004787,0.769000004787,1]},"o":{"a":0,"k":100},"w":{"a":0,"k":2},"lc":1,"lj":1,"ml":10,"bm":0,"nm":"Trazo 1","hd":false},{"ty":"tr","p":{"a":0,"k":[76.979,21.058]},"a":{"a":0,"k":[0,0]},"s":{"a":0,"k":[100,100]},"r":{"a":0,"k":0},"o":{"a":0,"k":100},"sk":{"a":0,"k":0},"sa":{"a":0,"k":0},"nm":"Transform"}],"nm":"Grupo 1","bm":0,"hd":false},{"ty":"gr","it":[{"ind":0,"ty":"sh","ks":{"a":0,"k":{"i":[[3.403,0],[0,0],[0,3.403],[0,0],[-3.403,0],[0,0],[0,-3.403],[0,0]],"o":[[0,0],[-3.403,0],[0,0],[0,-3.403],[0,0],[3.403,0],[0,0],[0,3.403]],"v":[[119.265,17.142],[-65.818,16.059],[-71.979,9.896],[-71.979,-9.896],[-65.818,-16.059],[119.265,-14.975],[125.427,-8.813],[125.427,10.98]],"c":true}},"nm":"Trazado 1","hd":false},{"ty":"fl","c":{"a":0,"k":[0.839215695858,0.839215695858,0.839215695858,1]},"o":{"a":0,"k":100},"r":1,"bm":0,"nm":"Relleno 1","hd":false},{"ty":"tr","p":{"a":0,"k":[76.979,21.058]},"a":{"a":0,"k":[0,0]},"s":{"a":0,"k":[100,100]},"r":{"a":0,"k":0},"o":{"a":0,"k":100},"sk":{"a":0,"k":0},"sa":{"a":0,"k":0},"nm":"Transform"}],"nm":"Grupo 2","bm":0,"hd":false}],"ip":0,"op":240,"st":0,"bm":0}]},{"id":"comp_3","layers":[{"ddd":0,"ind":1,"ty":4,"nm":"Screen","sr":1,"ks":{"o":{"a":0,"k":100},"r":{"a":0,"k":0},"p":{"a":0,"k":[1184.214,485.116,0]},"a":{"a":0,"k":[0,0,0]},"s":{"a":0,"k":[100,100,100]}},"ao":0,"shapes":[{"ty":"gr","it":[{"ind":0,"ty":"sh","ks":{"a":1,"k":[{"i":{"x":0.833,"y":0.833},"o":{"x":0.167,"y":0.167},"t":0,"s":[{"i":[[-4.004,-0.008],[0,0],[0.057,-10.328],[1.535,-0.006],[0,0],[4.429,-0.111],[0,0],[-9.315,0.052],[0,0]],"o":[[0,0],[10.467,-0.059],[0,0],[-53.235,0.194],[-5.523,0],[0,0],[-0.269,-12.833],[0,0],[5.523,0]],"v":[[-6.457,51.142],[56.216,51.141],[66.683,67.233],[63.608,71.302],[-95.951,71.722],[-115.813,71.768],[-192.166,71.662],[-183.121,51.082],[-27.804,51.188]],"c":true}]},{"t":10,"s":[{"i":[[0,-5.523],[0,0],[9.707,-0.709],[0,0],[0,0],[0,5.523],[0,0],[-5.523,0],[0,0]],"o":[[0,0],[-2.095,10.681],[0,0],[0,0],[-5.523,0],[0,0],[1.036,-6.098],[0,0],[5.523,0]],"v":[[95.665,-65.89],[69.153,51.248],[52.791,71.936],[52.663,71.936],[-95.845,72.256],[-105.209,64.18],[-80.076,-63.539],[-70.288,-74.821],[88.21,-74.821]],"c":true}]}]},"nm":"Trazado 1","hd":false},{"ty":"st","c":{"a":0,"k":[0.768627510819,0.768627510819,0.768627510819,1]},"o":{"a":0,"k":100},"w":{"a":0,"k":2},"lc":1,"lj":1,"ml":4,"bm":0,"nm":"Trazo 1","hd":false},{"ty":"fl","c":{"a":0,"k":[1,1,1,1]},"o":{"a":0,"k":100},"r":1,"bm":0,"nm":"Relleno 1","hd":false},{"ty":"tr","p":{"a":0,"k":[1.934,130.892]},"a":{"a":0,"k":[0,0]},"s":{"a":0,"k":[117.874,116.955]},"r":{"a":0,"k":0},"o":{"a":0,"k":100},"sk":{"a":0,"k":0},"sa":{"a":0,"k":0},"nm":"Transform"}],"nm":"Rectángulo 1","bm":0,"hd":false}],"ip":0,"op":240,"st":0,"bm":0},{"ddd":0,"ind":2,"ty":4,"nm":"Screen shadow","sr":1,"ks":{"o":{"a":0,"k":100},"r":{"a":0,"k":0},"p":{"a":1,"k":[{"i":{"x":0.833,"y":0.833},"o":{"x":0.167,"y":0.167},"t":0,"s":[1184.214,485.116,0],"to":[-2.25,0,0],"ti":[2.25,0,0]},{"t":10,"s":[1170.714,485.116,0]}]},"a":{"a":0,"k":[0,0,0]},"s":{"a":0,"k":[100,100,100]}},"ao":0,"shapes":[{"ty":"gr","it":[{"ind":0,"ty":"sh","ks":{"a":1,"k":[{"i":{"x":0.833,"y":0.833},"o":{"x":0.167,"y":0.167},"t":0,"s":[{"i":[[-4.004,-0.008],[0,0],[0.057,-10.328],[1.535,-0.006],[0,0],[4.429,-0.111],[0,0],[-9.315,0.052],[0,0]],"o":[[0,0],[10.467,-0.059],[0,0],[-53.235,0.194],[-5.523,0],[0,0],[-0.269,-12.833],[0,0],[5.523,0]],"v":[[-6.457,51.142],[56.216,51.141],[66.683,67.233],[63.608,71.302],[-95.951,71.722],[-115.813,71.768],[-192.166,71.662],[-183.121,51.082],[-27.804,51.188]],"c":true}]},{"t":10,"s":[{"i":[[0,-5.523],[0,0],[9.707,-0.709],[0,0],[0,0],[0,5.523],[0,0],[-5.523,0],[0,0]],"o":[[0,0],[-2.095,10.681],[0,0],[0,0],[-5.523,0],[0,0],[1.036,-6.098],[0,0],[5.523,0]],"v":[[95.665,-65.89],[69.153,51.248],[52.791,71.936],[52.663,71.936],[-95.845,72.256],[-105.209,64.18],[-80.076,-63.539],[-70.288,-74.821],[88.21,-74.821]],"c":true}]}]},"nm":"Trazado 1","hd":false},{"ty":"st","c":{"a":0,"k":[0.768627510819,0.768627510819,0.768627510819,1]},"o":{"a":0,"k":100},"w":{"a":0,"k":2},"lc":1,"lj":1,"ml":4,"bm":0,"nm":"Trazo 1","hd":false},{"ty":"fl","c":{"a":0,"k":[0.841023266315,0.838639855385,0.838639855385,1]},"o":{"a":0,"k":100},"r":1,"bm":0,"nm":"Relleno 1","hd":false},{"ty":"tr","p":{"a":0,"k":[1.934,130.892]},"a":{"a":0,"k":[0,0]},"s":{"a":0,"k":[117.874,116.955]},"r":{"a":0,"k":0},"o":{"a":0,"k":100},"sk":{"a":0,"k":0},"sa":{"a":0,"k":0},"nm":"Transform"}],"nm":"Rectángulo 1","bm":0,"hd":false}],"ip":0,"op":240,"st":0,"bm":0}]}],"layers":[{"ddd":0,"ind":1,"ty":0,"nm":"Ilustracion final hero","refId":"comp_0","sr":1,"ks":{"o":{"a":0,"k":100},"r":{"a":0,"k":0},"p":{"a":0,"k":[668,368,0]},"a":{"a":0,"k":[683,368,0]},"s":{"a":0,"k":[100,100,100]}},"ao":0,"w":1366,"h":736,"ip":0,"op":216,"st":0,"bm":0}],"markers":[]}